deprogressapi/__init__.py
deprogressapi/_version.py
deprogressapi/base.py
deprogressapi/print.py
deprogressapi/py.typed
deprogressapi/settings.py
deprogressapi/tree.py
deprogressapi-0.4.3.dist-info/Apache-2.0.txt
deprogressapi-0.4.3.dist-info/CC-BY-4.0.txt
deprogressapi-0.4.3.dist-info/CC0-1.0.txt
deprogressapi-0.4.3.dist-info/METADATA
deprogressapi-0.4.3.dist-info/WHEEL
deprogressapi-0.4.3.dist-info/top_level.txt
deprogressapi-0.4.3.dist-info/RECORD
